[{"id":1,"title":"title1","description":"description1","price":100,"thumbnail":"thumbnail","code":"A100","stock":10},{"id":2,"title":"title2","description":"description2","price":95,"thumbnail":"thumbnail","code":"B300","stock":20},{"id":3,"title":"title3","description":"description3","price":75,"thumbnail":"thumbnail","code":"J200","stock":12},{"id":4,"title":"title4","description":"description4","price":175,"thumbnail":"thumbnail","code":"K300","stock":12},{"id":5,"title":"title5","description":"description5","price":45,"thumbnail":"thumbnail","code":"L500","stock":112},{"id":6,"title":"title6","description":"description6","price":55,"thumbnail":"thumbnail","code":"M200","stock":132},{"id":7,"title":"title7","description":"description7","price":34,"thumbnail":"thumbnail","code":"N700","stock":512},{"id":8,"title":"title8","description":"description8","price":23,"thumbnail":"thumbnail","code":"P900","stock":16},{"id":9,"title":"title9","description":"description9","price":81,"thumbnail":"thumbnail","code":"R600","stock":172},{"id":10,"title":"title10","description":"description10","price":223,"thumbnail":"thumbnail","code":"X800","stock":15}]